vectorGPTBot/__init__.py
vectorGPTBot/vectorGPTBot.py
vectorGPTBot-0.1.6.dist-info/METADATA
vectorGPTBot-0.1.6.dist-info/WHEEL
vectorGPTBot-0.1.6.dist-info/top_level.txt
vectorGPTBot-0.1.6.dist-info/RECORD
