Metadata-Version: 2.1
Name: vectorGPTBot
Version: 0.1.6
Summary: A sample vectorGPTBot
Home-page: UNKNOWN
Author: wstart
License: Apache License 2.0
Keywords: vectorGPTBot
Platform: UNKNOWN
Classifier: Development Status :: 3 - Alpha
Classifier: Intended Audience :: Developers
Classifier: License :: OSI Approved :: MIT License
Classifier: Programming Language :: Python :: 3
Classifier: Programming Language :: Python :: 3.6
Classifier: Programming Language :: Python :: 3.7
Classifier: Programming Language :: Python :: 3.8
Classifier: Programming Language :: Python :: 3.9
Classifier: Programming Language :: Python :: Implementation :: CPython
Classifier: Programming Language :: Python :: Implementation :: PyPy
Requires-Dist: chromadb
Requires-Dist: modelscope
Requires-Dist: transformers
Requires-Dist: cpm-kernels
